fringe/__init__.py
fringe/backend/Numpy.py
fringe/backend/TensorFlow.py
fringe/backend/__init__.py
fringe/backend/core.py
fringe/modules/PhaseRecovery.py
fringe/modules/Scanner.py
fringe/modules/Simulator.py
fringe/modules/__init__.py
fringe/process/__init__.py
fringe/process/cpu.py
fringe/process/gpu.py
fringe/solvers/AngularSpectrum.py
fringe/solvers/__init__.py
fringe/solvers/base.py
fringe/utils/__init__.py
fringe/utils/io.py
fringe/utils/modifiers.py
fringe-1.0.7.dist-info/AUTHORS.rst
fringe-1.0.7.dist-info/LICENSE
fringe-1.0.7.dist-info/METADATA
fringe-1.0.7.dist-info/WHEEL
fringe-1.0.7.dist-info/top_level.txt
fringe-1.0.7.dist-info/RECORD
