Metadata-Version: 2.1
Name: fringe
Version: 1.0.7
Summary: Python implementation of computational optical propagation and digital holography.
Home-page: https://github.com/farhadnkm/fringe
Author: Farhad Niknam
Author-email: farhad.niknam.em@gmail.com
License: MIT license
Keywords: diffraction,angular spectrum,holography,holograms,phase recovery,
Classifier: Development Status :: 4 - Beta
Classifier: Intended Audience :: Science/Research
Classifier: License :: OSI Approved :: MIT License
Classifier: Programming Language :: Python :: 3
Classifier: Programming Language :: Python :: 3.6
Classifier: Programming Language :: Python :: 3.7
Classifier: Programming Language :: Python :: 3.8
Classifier: Programming Language :: Python :: 3.9
Classifier: Programming Language :: Python :: 3.10
Classifier: Programming Language :: Python :: 3.11
Classifier: Topic :: Scientific/Engineering :: Image Processing
Requires-Python: >=3.6, <4
License-File: LICENSE
License-File: AUTHORS.rst
Requires-Dist: numpy (>=1.10.0)
Requires-Dist: tensorflow (>=2.0.0)
Requires-Dist: scikit-image (>=0.10.1)
